{
    "timestamp": "2012-08-09T21:08:24Z", 
    "size": 89164, 
    "sections": [
        {
            "index": "1", 
            "level": "2", 
            "fromtitle": "Birth_control", 
            "toclevel": 1, 
            "number": "1", 
            "byteoffset": 1183, 
            "line": "Definition", 
            "anchor": "Definition"
        }, 
        {
            "index": "2", 
            "level": "2", 
            "fromtitle": "Birth_control", 
            "toclevel": 1, 
            "number": "2", 
            "byteoffset": 8615, 
            "line": "Methods", 
            "anchor": "Methods"
        }, 
        {
            "index": "3", 
            "level": "3", 
            "fromtitle": "Birth_control", 
            "toclevel": 2, 
            "number": "2.1", 
            "byteoffset": 9890, 
            "line": "Barrier", 
            "anchor": "Barrier"
        }, 
        {
            "index": "4", 
            "level": "3", 
            "fromtitle": "Birth_control", 
            "toclevel": 2, 
            "number": "2.2", 
            "byteoffset": 10229, 
            "line": "Hormonal", 
            "anchor": "Hormonal"
        }, 
        {
            "index": "5", 
            "level": "3", 
            "fromtitle": "Birth_control", 
            "toclevel": 2, 
            "number": "2.3", 
            "byteoffset": 10947, 
            "line": "Sterilization", 
            "anchor": "Sterilization"
        }, 
        {
            "index": "6", 
            "level": "3", 
            "fromtitle": "Birth_control", 
            "toclevel": 2, 
            "number": "2.4", 
            "byteoffset": 11632, 
            "line": "Behavioral", 
            "anchor": "Behavioral"
        }, 
        {
            "index": "7", 
            "level": "4", 
            "fromtitle": "Birth_control", 
            "toclevel": 3, 
            "number": "2.4.1", 
            "byteoffset": 11889, 
            "line": "Lactational", 
            "anchor": "Lactational"
        }, 
        {
            "index": "8", 
            "level": "4", 
            "fromtitle": "Birth_control", 
            "toclevel": 3, 
            "number": "2.4.2", 
            "byteoffset": 12141, 
            "line": "Fertility awareness", 
            "anchor": "Fertility_awareness"
        }, 
        {
            "index": "9", 
            "level": "4", 
            "fromtitle": "Birth_control", 
            "toclevel": 3, 
            "number": "2.4.3", 
            "byteoffset": 13724, 
            "line": "Coitus interruptus", 
            "anchor": "Coitus_interruptus"
        }, 
        {
            "index": "10", 
            "level": "4", 
            "fromtitle": "Birth_control", 
            "toclevel": 3, 
            "number": "2.4.4", 
            "byteoffset": 14834, 
            "line": "Sexual abstinence", 
            "anchor": "Sexual_abstinence"
        }, 
        {
            "index": "11", 
            "level": "3", 
            "fromtitle": "Birth_control", 
            "toclevel": 2, 
            "number": "2.5", 
            "byteoffset": 18562, 
            "line": "Emergency contraceptive", 
            "anchor": "Emergency_contraceptive"
        }, 
        {
            "index": "12", 
            "level": "2", 
            "fromtitle": "Birth_control", 
            "toclevel": 1, 
            "number": "3", 
            "byteoffset": 20185, 
            "line": "Effectiveness", 
            "anchor": "Effectiveness"
        }, 
        {
            "index": "13", 
            "level": "3", 
            "fromtitle": "Birth_control", 
            "toclevel": 2, 
            "number": "3.1", 
            "byteoffset": 27963, 
            "line": "Dual protection", 
            "anchor": "Dual_protection"
        }, 
        {
            "index": "14", 
            "level": "2", 
            "fromtitle": "Birth_control", 
            "toclevel": 1, 
            "number": "4", 
            "byteoffset": 30647, 
            "line": "Adverse effects", 
            "anchor": "Adverse_effects"
        }, 
        {
            "index": "15", 
            "level": "2", 
            "fromtitle": "Birth_control", 
            "toclevel": 1, 
            "number": "5", 
            "byteoffset": 31423, 
            "line": "Mechanisms of action", 
            "anchor": "Mechanisms_of_action"
        }, 
        {
            "index": "16", 
            "level": "2", 
            "fromtitle": "Birth_control", 
            "toclevel": 1, 
            "number": "6", 
            "byteoffset": 35883, 
            "line": "Prevalence", 
            "anchor": "Prevalence"
        }, 
        {
            "index": "17", 
            "level": "3", 
            "fromtitle": "Birth_control", 
            "toclevel": 2, 
            "number": "6.1", 
            "byteoffset": 37156, 
            "line": "United States", 
            "anchor": "United_States"
        }, 
        {
            "index": "18", 
            "level": "2", 
            "fromtitle": "Birth_control", 
            "toclevel": 1, 
            "number": "7", 
            "byteoffset": 39106, 
            "line": "History", 
            "anchor": "History"
        }, 
        {
            "index": "19", 
            "level": "3", 
            "fromtitle": "Birth_control", 
            "toclevel": 2, 
            "number": "7.1", 
            "byteoffset": 39211, 
            "line": "Early history", 
            "anchor": "Early_history"
        }, 
        {
            "index": "20", 
            "level": "4", 
            "fromtitle": "Birth_control", 
            "toclevel": 3, 
            "number": "7.1.1", 
            "byteoffset": 39231, 
            "line": "Ancient Mesopotamia, Egypt and Rome", 
            "anchor": "Ancient_Mesopotamia.2C_Egypt_and_Rome"
        }, 
        {
            "index": "21", 
            "level": "4", 
            "fromtitle": "Birth_control", 
            "toclevel": 3, 
            "number": "7.1.2", 
            "byteoffset": 42159, 
            "line": "Religious texts", 
            "anchor": "Religious_texts"
        }, 
        {
            "index": "22", 
            "level": "4", 
            "fromtitle": "Birth_control", 
            "toclevel": 3, 
            "number": "7.1.3", 
            "byteoffset": 43058, 
            "line": "Ancient China", 
            "anchor": "Ancient_China"
        }, 
        {
            "index": "23", 
            "level": "4", 
            "fromtitle": "Birth_control", 
            "toclevel": 3, 
            "number": "7.1.4", 
            "byteoffset": 43717, 
            "line": "India", 
            "anchor": "India"
        }, 
        {
            "index": "24", 
            "level": "4", 
            "fromtitle": "Birth_control", 
            "toclevel": 3, 
            "number": "7.1.5", 
            "byteoffset": 44239, 
            "line": "Early Islam", 
            "anchor": "Early_Islam"
        }, 
        {
            "index": "25", 
            "level": "3", 
            "fromtitle": "Birth_control", 
            "toclevel": 2, 
            "number": "7.2", 
            "byteoffset": 45127, 
            "line": "Modern era", 
            "anchor": "Modern_era"
        }, 
        {
            "index": "26", 
            "level": "3", 
            "fromtitle": "Birth_control", 
            "toclevel": 2, 
            "number": "7.3", 
            "byteoffset": 49445, 
            "line": "Entymology", 
            "anchor": "Entymology"
        }, 
        {
            "index": "27", 
            "level": "2", 
            "fromtitle": "Birth_control", 
            "toclevel": 1, 
            "number": "8", 
            "byteoffset": 53232, 
            "line": "Society and culture", 
            "anchor": "Society_and_culture"
        }, 
        {
            "index": "28", 
            "level": "3", 
            "fromtitle": "Birth_control", 
            "toclevel": 2, 
            "number": "8.1", 
            "byteoffset": 53256, 
            "line": "Birth control and public policy", 
            "anchor": "Birth_control_and_public_policy"
        }, 
        {
            "index": "29", 
            "level": "3", 
            "fromtitle": "Birth_control", 
            "toclevel": 2, 
            "number": "8.2", 
            "byteoffset": 56346, 
            "line": "Birth control movement", 
            "anchor": "Birth_control_movement"
        }, 
        {
            "index": "30", 
            "level": "3", 
            "fromtitle": "Birth_control", 
            "toclevel": 2, 
            "number": "8.3", 
            "byteoffset": 61218, 
            "line": "Legal status", 
            "anchor": "Legal_status"
        }, 
        {
            "index": "31", 
            "level": "4", 
            "fromtitle": "Birth_control", 
            "toclevel": 3, 
            "number": "8.3.1", 
            "byteoffset": 61237, 
            "line": "United States", 
            "anchor": "United_States_2"
        }, 
        {
            "index": "32", 
            "level": "4", 
            "fromtitle": "Birth_control", 
            "toclevel": 3, 
            "number": "8.3.2", 
            "byteoffset": 62865, 
            "line": "France", 
            "anchor": "France"
        }, 
        {
            "index": "33", 
            "level": "3", 
            "fromtitle": "Birth_control", 
            "toclevel": 2, 
            "number": "8.4", 
            "byteoffset": 63676, 
            "line": "Religious views", 
            "anchor": "Religious_views"
        }, 
        {
            "index": "34", 
            "level": "3", 
            "fromtitle": "Birth_control", 
            "toclevel": 2, 
            "number": "8.5", 
            "byteoffset": 66603, 
            "line": "Cultural attitudes", 
            "anchor": "Cultural_attitudes"
        }, 
        {
            "index": "35", 
            "level": "3", 
            "fromtitle": "Birth_control", 
            "toclevel": 2, 
            "number": "8.6", 
            "byteoffset": 69163, 
            "line": "Sex education", 
            "anchor": "Sex_education"
        }, 
        {
            "index": "36", 
            "level": "3", 
            "fromtitle": "Birth_control", 
            "toclevel": 2, 
            "number": "8.7", 
            "byteoffset": 72702, 
            "line": "Misconceptions", 
            "anchor": "Misconceptions"
        }, 
        {
            "index": "37", 
            "level": "2", 
            "fromtitle": "Birth_control", 
            "toclevel": 1, 
            "number": "9", 
            "byteoffset": 77399, 
            "line": "Research", 
            "anchor": "Research"
        }, 
        {
            "index": "38", 
            "level": "3", 
            "fromtitle": "Birth_control", 
            "toclevel": 2, 
            "number": "9.1", 
            "byteoffset": 77412, 
            "line": "For females", 
            "anchor": "For_females"
        }, 
        {
            "index": "39", 
            "level": "3", 
            "fromtitle": "Birth_control", 
            "toclevel": 2, 
            "number": "9.2", 
            "byteoffset": 81041, 
            "line": "For males", 
            "anchor": "For_males"
        }, 
        {
            "index": "40", 
            "level": "2", 
            "fromtitle": "Birth_control", 
            "toclevel": 1, 
            "number": "10", 
            "byteoffset": 84093, 
            "line": "In other animals", 
            "anchor": "In_other_animals"
        }, 
        {
            "index": "41", 
            "level": "2", 
            "fromtitle": "Birth_control", 
            "toclevel": 1, 
            "number": "11", 
            "byteoffset": 86672, 
            "line": "References", 
            "anchor": "References"
        }, 
        {
            "index": "42", 
            "level": "2", 
            "fromtitle": "Birth_control", 
            "toclevel": 1, 
            "number": "12", 
            "byteoffset": 86714, 
            "line": "External links", 
            "anchor": "External_links"
        }
    ], 
    "revid": 506621944, 
    "title": "Birth control"
}